bluecat_automation_toolkit/__init__.py
bluecat_automation_toolkit/_version.py
bluecat_automation_toolkit/cli.py
bluecat_automation_toolkit/_internal/__init__.py
bluecat_automation_toolkit/_internal/cli.py
bluecat_automation_toolkit/_internal/copyrights.py
bluecat_automation_toolkit/_internal/output.py
bluecat_automation_toolkit/_internal/jinja_templates/_autoloaded.html
bluecat_automation_toolkit/_internal/jinja_templates/utils.html
bluecat_automation_toolkit/_internal/templates/license_file/__init__.py
bluecat_automation_toolkit/_internal/templates/minimal/__init__.py
bluecat_automation_toolkit/_internal/templates/minimal/definition.py
bluecat_automation_toolkit/_internal/templates/minimal/files/.dockerignore
bluecat_automation_toolkit/_internal/templates/minimal/files/.gitignore
bluecat_automation_toolkit/_internal/templates/minimal/files/Dockerfile
bluecat_automation_toolkit/_internal/templates/minimal/files/Makefile
bluecat_automation_toolkit/_internal/templates/minimal/files/workspace/config.json.sample
bluecat_automation_toolkit/_internal/templates/minimal/files/workspace/config.py.sample
bluecat_automation_toolkit/_internal/templates/minimal/files/workspace/permissions.json.sample
bluecat_automation_toolkit/_internal/templates/minimal/files/workspace/workflows/__init__.py
bluecat_automation_toolkit/_internal/templates/minimal_ui/__init__.py
bluecat_automation_toolkit/_internal/templates/minimal_ui/definition.py
bluecat_automation_toolkit/_internal/templates/minimal_ui/files/.gitignore
bluecat_automation_toolkit/_internal/templates/minimal_ui/files/Makefile
bluecat_automation_toolkit/_internal/templates/minimal_ui/files/projects/workflow_name/Makefile
bluecat_automation_toolkit/_internal/templates/minimal_ui/files/projects/workflow_name/README.md
bluecat_automation_toolkit/_internal/templates/minimal_ui/files/projects/workflow_name/ui_project_name/.eslintrc.js
bluecat_automation_toolkit-1.0.0b2.dist-info/LICENSE
bluecat_automation_toolkit-1.0.0b2.dist-info/METADATA
bluecat_automation_toolkit-1.0.0b2.dist-info/WHEEL
bluecat_automation_toolkit-1.0.0b2.dist-info/entry_points.txt
bluecat_automation_toolkit-1.0.0b2.dist-info/top_level.txt
bluecat_automation_toolkit-1.0.0b2.dist-info/RECORD
