Metadata-Version: 2.1
Name: bluecat-automation-toolkit
Version: 1.0.0b2
Summary: Utility tool for working with Bluecat Gateway workflow
Author: BlueCat
Maintainer-email: Stargate <ENG-Stargate-Team@bluecatnetworks.com>
License: # Copyright 2023 BlueCat Networks Inc.
Project-URL: homepage, https://docs.bluecatnetworks.com
Project-URL: repository, https://gitlab.bluecatlabs.net/dns-integrity/stargate/automation-toolkit
Classifier: License :: OSI Approved :: MIT License
Classifier: Programming Language :: Python :: 3.9
Requires-Python: ~=3.9.0
License-File: LICENSE
Requires-Dist: click >=8.1.3
Requires-Dist: jinja2 >=3.1.2
